{
  "name": "ZQshare",
  "tagline": "目前国内还没有一款现成的、支持SSL的分享插件。而ZQshare SSL打破了这个僵局。",
  "body": "# 欢迎来到ZQshare！\r\nZQshare是国内唯一支持SSL的分享插件。\r\n\r\n##1.什么是ZQshare SSL？\r\n      ZQshare SSL 是一款由 xtl 搭建的公共分享平台，基于百度分享，具有百度分享99%的功能。是主流分享引擎中唯一支持ssl的。它的诞生离不开hrwhisper/baiduShare 开源项目。您仍可在百度分享开放平台查看统计。\r\n##2.为什么要ZQshare SSL？\r\n      ZQshare SSL 是主流分享引擎中唯一支持ssl的。\r\n##3.ZQshare SSL怎么样？\r\n      您可点击右侧“分享”浮窗，选择一段文本或移到我的头像上测试。\r\n##4.ZQshare SSL源代码开放吗？\r\n      ZQshare SSL 源代码完全开放，您可以在这里下载。（记得点星星哦！）\r\n##5.ZQshare SSL如何使用？\r\n      请先至 http://share.baidu.com 自定义获取代码，并到 https://share.zqjs.tk/convert.php 转换。 然后，按照百度分享正常使用步骤，将获取的ZQshare代码复制到页面中去。（其实转换工具仅把域名替换了下，因为用的内核是一样的。）\r\n\r\n\r\n# 联系？\r\n[QQ](http://wpa.qq.com/msgrd?V=3&uin=2317305587&site=中国青年技术论坛&menu=yes&from=discuz)  [mail](mailto:xtl@xtlsoft.top)\r\n\r\n<!--ZQshare begin-->\r\n<script>window._bd_share_config={\"common\":{\"bdSnsKey\":{},\"bdText\":\"\",\"bdMini\":\"2\",\"bdMiniList\":false,\"bdPic\":\"\",\"bdStyle\":\"1\",\"bdSize\":\"16\"},\"slide\":{\"type\":\"slide\",\"bdImg\":\"6\",\"bdPos\":\"right\",\"bdTop\":\"100\"},\"image\":{\"viewList\":[\"qzone\",\"tsina\",\"tqq\",\"renren\",\"weixin\"],\"viewText\":\"分享到：\",\"viewSize\":\"16\"},\"selectShare\":{\"bdContainerClass\":null,\"bdSelectMiniList\":[\"qzone\",\"tsina\",\"tqq\",\"renren\",\"weixin\"]}};with(document)0[(getElementsByTagName('head')[0]||body).appendChild(createElement('script')).src='https://share.zqjs.tk/static/api/js/share.js?v=89860593.js?cdnversion=' ~(-new Date()/36e5)];</script>\r\n<!--ZQshare end-->\r\n",
  "note": "Don't delete this file! It's used internally to help with page regeneration."
}